DataAnalysis/__init__.py
DataAnalysis-0.0.4.dist-info/LICENSE
DataAnalysis-0.0.4.dist-info/METADATA
DataAnalysis-0.0.4.dist-info/WHEEL
DataAnalysis-0.0.4.dist-info/top_level.txt
DataAnalysis-0.0.4.dist-info/RECORD
